r7assistant/__init__.py
r7assistant/assistant.py
r7assistant/microphone.py
r7assistant/recognizer.py
r7assistant-0.0.1.dist-info/LICENSE.md
r7assistant-0.0.1.dist-info/METADATA
r7assistant-0.0.1.dist-info/WHEEL
r7assistant-0.0.1.dist-info/top_level.txt
r7assistant-0.0.1.dist-info/RECORD
